redflag/__init__.py
redflag/distributions.py
redflag/imbalance.py
redflag/importance.py
redflag/independence.py
redflag/markov.py
redflag/outliers.py
redflag/pandas.py
redflag/sklearn.py
redflag/target.py
redflag/utils.py
redflag-0.5.0.dist-info/AUTHORS.md
redflag-0.5.0.dist-info/LICENSE
redflag-0.5.0.dist-info/METADATA
redflag-0.5.0.dist-info/WHEEL
redflag-0.5.0.dist-info/top_level.txt
redflag-0.5.0.dist-info/RECORD
