Metadata-Version: 2.1
Name: redflag
Version: 0.5.0
Summary: Safety net for machine learning pipelines.
Author-email: Matt Hall <kwinkunks@gmail.com>
License: Apache License
Project-URL: documentation, https://scienxlab.org/redflag
Project-URL: repository, https://github.com/scienxlab/redflag
Keywords: machine learning,data science,quality assurance
Classifier: Intended Audience :: Science/Research
Classifier: Topic :: Scientific/Engineering :: Information Analysis
Classifier: Development Status :: 4 - Beta
Classifier: Natural Language :: English
Classifier: Programming Language :: Python :: 3.8
Classifier: Programming Language :: Python :: 3.9
Classifier: Programming Language :: Python :: 3.10
Classifier: Programming Language :: Python :: 3.11
Classifier: Programming Language :: Python :: 3.12
Classifier: License :: OSI Approved :: Apache Software License
Classifier: Operating System :: OS Independent
Requires-Python: >=3.8
License-File: LICENSE
License-File: AUTHORS.md
Requires-Dist: numpy <2.0
Requires-Dist: scipy !=1.10.0
Requires-Dist: scikit-learn
Provides-Extra: dev
Requires-Dist: setuptools ; extra == 'dev'
Requires-Dist: build ; extra == 'dev'
Requires-Dist: mypy ; extra == 'dev'
Requires-Dist: types-setuptools ; extra == 'dev'
Requires-Dist: pytest ; extra == 'dev'
Requires-Dist: coverage[toml] ; extra == 'dev'
Requires-Dist: pytest-cov ; extra == 'dev'
Requires-Dist: sphinx ; extra == 'dev'
Requires-Dist: sphinxcontrib-apidoc ; extra == 'dev'
Requires-Dist: sphinx-copybutton ; extra == 'dev'
Requires-Dist: furo ; extra == 'dev'
Requires-Dist: myst-nb ; extra == 'dev'
Requires-Dist: jupyter ; extra == 'dev'
Requires-Dist: pandas ; extra == 'dev'
Requires-Dist: seaborn ; extra == 'dev'
